sdutilities/__init__.py
sdutilities/acsclient.py
sdutilities/aggregator.py
sdutilities/awsclient.py
sdutilities/datalink.py
sdutilities/futures.py
sdutilities/general.py
sdutilities/logger.py
sdutilities/matching.py
sdutilities/cfg_tables/grp_table_cfg.json
sdutilities/cfg_tables/sample_table_cfg.json
sdutilities-1.3.5.dist-info/LICENSE
sdutilities-1.3.5.dist-info/METADATA
sdutilities-1.3.5.dist-info/WHEEL
sdutilities-1.3.5.dist-info/top_level.txt
sdutilities-1.3.5.dist-info/RECORD
