Metadata-Version: 2.1
Name: sdutilities
Version: 1.3.5
Summary: This package is intended to implement uniformity across                  SD Data Science projects.
Author: Stephen Olsen, Taylor Ward, McKenna Magoffin, Jaffar Shaik, Evan Tucker, Chintan Dalal
Author-email: taylorward@sociallydetermined.com,                   mckennamagoffin@sociallydetermined.com,                   chintandalal@sociallydetermined.com
Maintainer: Chintan Dalal
Maintainer-email: chintandalal@sociallydetermined.com
Classifier: Programming Language :: Python :: 3
Classifier: License :: Other/Proprietary License
Classifier: Operating System :: OS Independent
Requires-Python: >=3.9
License-File: LICENSE
Requires-Dist: setuptools >=61.2.0
Requires-Dist: zipp >=3.19.1
Requires-Dist: requests >=2.32.2
Requires-Dist: pandas >=1.2.3
Requires-Dist: numpy <=1.23.5
Requires-Dist: certifi >=2023.7.22
Requires-Dist: sdcensus >=0.8.20
Requires-Dist: us >=2.0.2
Requires-Dist: sqlalchemy >=1.3.9
Requires-Dist: matplotlib >=3.5.1
Requires-Dist: Pillow >=10.0.1
Requires-Dist: boto3 >=1.17.43
Requires-Dist: botocore >=1.19.52
Requires-Dist: python-Levenshtein >=0.12.2
Requires-Dist: fuzzywuzzy >=0.18.0
Requires-Dist: fonttools >=4.47.2
Requires-Dist: psycopg2 >=2.9.9
Requires-Dist: pytest-mock >=3.12.0
Requires-Dist: httpx >=0.26.0
